CHANGELOG
LICENSE
MANIFEST.in
README.rst
requirements.txt
setup.py
minion/__init__.py
minion/errors.py
minion/helpers.py
minion/parser.py
minion/client/__init__.py
minion/client/__main__.py
minion/client/core.py
minion/client/templates/minion.yml
minion/server/__init__.py
minion/server/__main__.py
minion/server/app.py
minion/server/config.py
minion/server/core.py
minion/server/models.py
minion/server/routes.py
minion/server/static/css/minion.css
minion/server/static/images/minion.png
minion/server/templates/index.html
minion_ci.egg-info/PKG-INFO
minion_ci.egg-info/SOURCES.txt
minion_ci.egg-info/dependency_links.txt
minion_ci.egg-info/entry_points.txt
minion_ci.egg-info/requires.txt
minion_ci.egg-info/top_level.txt