Metadata-Version: 1.1
Name: minion-ci
Version: 0.0.7
Summary: minimalist, decentralized, flexible Continuous Integration Server for hackers
Home-page: https://github.com/timofurrer/minion-ci
Author: Timo Furrer
Author-email: tuxtimo@gmail.com
License: MIT
Keywords: minion-ci,minimalist,simple,flexible,decentral,ci,continuous integration,server,git,github,source,code,docker,container
Platform: UNKNOWN
Classifier: Programming Language :: Python
Classifier: Programming Language :: Python :: 3
Classifier: Programming Language :: Python :: 3.4
Classifier: Programming Language :: Python :: 3.5
Classifier: Operating System :: OS Independent
Classifier: Environment :: Console
Classifier: License :: OSI Approved :: MIT License
Classifier: Intended Audience :: End Users/Desktop
Classifier: Topic :: Utilities
